vagrepo/__init__.py
vagrepo/__main__.py
vagrepo/cli.py
vagrepo/repository.py
vagrepo-0.1.1a1.dist-info/DESCRIPTION.rst
vagrepo-0.1.1a1.dist-info/METADATA
vagrepo-0.1.1a1.dist-info/RECORD
vagrepo-0.1.1a1.dist-info/WHEEL
vagrepo-0.1.1a1.dist-info/entry_points.txt
vagrepo-0.1.1a1.dist-info/metadata.json
vagrepo-0.1.1a1.dist-info/top_level.txt
