Metadata-Version: 2.0
Name: vagrepo
Version: 0.1.1a1
Summary: A local vagrant box repository manager.
Home-page: https://github.com/matthijsbos/vagrepo
Author: Matthijs Bos
Author-email: matthijs_vlaarbos@hotmail.com
License: Apache License 2.0
Keywords: Vagrant repository Vagrant-boxes
Platform: UNKNOWN
Classifier: Development Status :: 3 - Alpha
Classifier: Environment :: Console
Classifier: Intended Audience :: Developers
Classifier: Intended Audience :: Information Technology
Classifier: License :: OSI Approved :: Apache Software License
Classifier: Programming Language :: Python :: 3.4
Classifier: Programming Language :: Python :: 3.5
Classifier: Programming Language :: Python :: 3.6
